MachineFailure/__init__.py
MachineFailure/functions.py
MachineFailure/encoders/__init__.py
MachineFailure/encoders/encoder_dict.pkl
MachineFailure/normalizers/__init__.py
MachineFailure/normalizers/normalizer_dict.pkl
MachineFailure/pre_trained_models/FailPredictor.pkl
MachineFailure/pre_trained_models/__init__.py
MachineFailure-0.0.1.dist-info/METADATA
MachineFailure-0.0.1.dist-info/WHEEL
MachineFailure-0.0.1.dist-info/top_level.txt
MachineFailure-0.0.1.dist-info/RECORD
