Metadata-Version: 2.1
Name: MachineFailure
Version: 0.0.1
Summary: Random Forest model to predict machine failure
Author: Kishore
Classifier: Programming Language :: Python :: 3
Classifier: Operating System :: OS Independent
Requires-Python: >=3.7
